UniversalGPIO/GPIO.py
UniversalGPIO/__init__.py
UniversalGPIO-1.0.4.dist-info/LICENSE
UniversalGPIO-1.0.4.dist-info/METADATA
UniversalGPIO-1.0.4.dist-info/WHEEL
UniversalGPIO-1.0.4.dist-info/top_level.txt
UniversalGPIO-1.0.4.dist-info/RECORD
