Metadata-Version: 2.1
Name: UniversalGPIO
Version: 1.0.4
Summary: Python Library for interfacing GPIO Pins on Linux based Routers, Network Devices, and embeded Devices like Rasapberry pi and OpenWRT based Routers.
Home-page: https://github.com/harshsinghvi/UniversalGPIO
Author: Harsh Singhvi
Author-email: root@harshsinghvi.com
License: MIT
Platform: UNKNOWN
Classifier: License :: OSI Approved :: MIT License
Classifier: Programming Language :: Python
Classifier: Programming Language :: Python :: 3
Classifier: Programming Language :: Python :: 3.7
Classifier: Programming Language :: Python :: Implementation :: CPython
Classifier: Programming Language :: Python :: Implementation :: PyPy
Requires-Python: >=3.6.0
Requires-Dist: flask
Requires-Dist: flask-cors
